[
  {
    "ContainingType": "DailyApp.API.Controllers.AccountController",
    "Method": "Login",
    "RelativePath": "api/Account/Login",
    "HttpMethod": "GET",
    "IsController": true,
    "Order": 0,
    "Parameters": [
      {
        "Name": "account",
        "Type": "System.String",
        "IsRequired": false
      },
      {
        "Name": "pwd",
        "Type": "System.String",
        "IsRequired": false
      }
    ],
    "ReturnTypes": []
  },
  {
    "ContainingType": "DailyApp.API.Controllers.AccountController",
    "Method": "Reg",
    "RelativePath": "api/Account/Reg",
    "HttpMethod": "POST",
    "IsController": true,
    "Order": 0,
    "Parameters": [
      {
        "Name": "accountInfoDTO",
        "Type": "DailyApp.API.DTOs.AccountInfoDTO",
        "IsRequired": true
      }
    ],
    "ReturnTypes": []
  },
  {
    "ContainingType": "DailyApp.API.Controllers.MemoController",
    "Method": "AddMomo",
    "RelativePath": "api/Memo/AddMomo",
    "HttpMethod": "POST",
    "IsController": true,
    "Order": 0,
    "Parameters": [
      {
        "Name": "memoDTO",
        "Type": "DailyApp.API.DTOs.MemoDTO",
        "IsRequired": true
      }
    ],
    "ReturnTypes": []
  },
  {
    "ContainingType": "DailyApp.API.Controllers.MemoController",
    "Method": "DelMemo",
    "RelativePath": "api/Memo/DelMemo",
    "HttpMethod": "DELETE",
    "IsController": true,
    "Order": 0,
    "Parameters": [
      {
        "Name": "memoId",
        "Type": "System.Int32",
        "IsRequired": false
      }
    ],
    "ReturnTypes": []
  },
  {
    "ContainingType": "DailyApp.API.Controllers.MemoController",
    "Method": "EditMemo",
    "RelativePath": "api/Memo/EditMemo",
    "HttpMethod": "PUT",
    "IsController": true,
    "Order": 0,
    "Parameters": [
      {
        "Name": "memoDTO",
        "Type": "DailyApp.API.DTOs.MemoDTO",
        "IsRequired": true
      }
    ],
    "ReturnTypes": []
  },
  {
    "ContainingType": "DailyApp.API.Controllers.MemoController",
    "Method": "QueryMemo",
    "RelativePath": "api/Memo/QueryMemo",
    "HttpMethod": "GET",
    "IsController": true,
    "Order": 0,
    "Parameters": [
      {
        "Name": "title",
        "Type": "System.String",
        "IsRequired": false
      }
    ],
    "ReturnTypes": []
  },
  {
    "ContainingType": "DailyApp.API.Controllers.MemoController",
    "Method": "StatMomo",
    "RelativePath": "api/Memo/StatMomo",
    "HttpMethod": "GET",
    "IsController": true,
    "Order": 0,
    "Parameters": [],
    "ReturnTypes": []
  },
  {
    "ContainingType": "DailyApp.API.Controllers.WaitController",
    "Method": "AddWait",
    "RelativePath": "api/Wait/AddWait",
    "HttpMethod": "POST",
    "IsController": true,
    "Order": 0,
    "Parameters": [
      {
        "Name": "waitDTO",
        "Type": "DailyApp.API.DTOs.WaitDTO",
        "IsRequired": true
      }
    ],
    "ReturnTypes": []
  },
  {
    "ContainingType": "DailyApp.API.Controllers.WaitController",
    "Method": "DelWait",
    "RelativePath": "api/Wait/DelWait",
    "HttpMethod": "DELETE",
    "IsController": true,
    "Order": 0,
    "Parameters": [
      {
        "Name": "waitId",
        "Type": "System.Int32",
        "IsRequired": false
      }
    ],
    "ReturnTypes": []
  },
  {
    "ContainingType": "DailyApp.API.Controllers.WaitController",
    "Method": "EditWait",
    "RelativePath": "api/Wait/EditWait",
    "HttpMethod": "PUT",
    "IsController": true,
    "Order": 0,
    "Parameters": [
      {
        "Name": "newDto",
        "Type": "DailyApp.API.DTOs.WaitDTO",
        "IsRequired": true
      }
    ],
    "ReturnTypes": []
  },
  {
    "ContainingType": "DailyApp.API.Controllers.WaitController",
    "Method": "GetWaiting",
    "RelativePath": "api/Wait/GetWaiting",
    "HttpMethod": "GET",
    "IsController": true,
    "Order": 0,
    "Parameters": [],
    "ReturnTypes": []
  },
  {
    "ContainingType": "DailyApp.API.Controllers.WaitController",
    "Method": "QueryWait",
    "RelativePath": "api/Wait/QueryWait",
    "HttpMethod": "GET",
    "IsController": true,
    "Order": 0,
    "Parameters": [
      {
        "Name": "title",
        "Type": "System.String",
        "IsRequired": false
      },
      {
        "Name": "status",
        "Type": "System.Nullable\u00601[[System.Int32, System.Private.CoreLib, Version=6.0.0.0, Culture=neutral, PublicKeyToken=7cec85d7bea7798e]]",
        "IsRequired": false
      }
    ],
    "ReturnTypes": []
  },
  {
    "ContainingType": "DailyApp.API.Controllers.WaitController",
    "Method": "StatWait",
    "RelativePath": "api/Wait/StatWait",
    "HttpMethod": "GET",
    "IsController": true,
    "Order": 0,
    "Parameters": [],
    "ReturnTypes": []
  },
  {
    "ContainingType": "DailyApp.API.Controllers.WaitController",
    "Method": "UpdateStatus",
    "RelativePath": "api/Wait/UpdateStatus",
    "HttpMethod": "PUT",
    "IsController": true,
    "Order": 0,
    "Parameters": [
      {
        "Name": "newStatusDto",
        "Type": "DailyApp.API.DTOs.WaitDTO",
        "IsRequired": true
      }
    ],
    "ReturnTypes": []
  },
  {
    "ContainingType": "DailyApp.API.Controllers.WeatherForecastController",
    "Method": "Get",
    "RelativePath": "WeatherForecast",
    "HttpMethod": "GET",
    "IsController": true,
    "Order": 0,
    "Parameters": [],
    "ReturnTypes": [
      {
        "Type": "System.Collections.Generic.IEnumerable\u00601[[DailyApp.API.WeatherForecast, DailyApp.API, Version=1.0.0.0, Culture=neutral, PublicKeyToken=null]]",
        "MediaTypes": [
          "text/plain",
          "application/json",
          "text/json"
        ],
        "StatusCode": 200
      }
    ],
    "EndpointName": "GetWeatherForecast"
  }
]